check_manifest.py
check_manifest-0.50.dist-info/LICENSE.rst
check_manifest-0.50.dist-info/METADATA
check_manifest-0.50.dist-info/WHEEL
check_manifest-0.50.dist-info/entry_points.txt
check_manifest-0.50.dist-info/top_level.txt
check_manifest-0.50.dist-info/RECORD
