Metadata-Version: 2.1
Name: check-manifest
Version: 0.50
Summary: Check MANIFEST.in in a Python source package for completeness
Home-page: https://github.com/mgedmin/check-manifest
Author: Marius Gedminas
Author-email: marius@gedmin.as
License: MIT
Keywords: distutils,setuptools,packaging,manifest,checker,linter
Classifier: Development Status :: 4 - Beta
Classifier: Environment :: Console
Classifier: Intended Audience :: Developers
Classifier: License :: OSI Approved :: MIT License
Classifier: Operating System :: OS Independent
Classifier: Programming Language :: Python
Classifier: Programming Language :: Python :: 3
Classifier: Programming Language :: Python :: 3.7
Classifier: Programming Language :: Python :: 3.8
Classifier: Programming Language :: Python :: 3.9
Classifier: Programming Language :: Python :: 3.10
Classifier: Programming Language :: Python :: 3.11
Classifier: Programming Language :: Python :: 3.12
Classifier: Programming Language :: Python :: 3.13
Classifier: Programming Language :: Python :: Implementation :: CPython
Classifier: Programming Language :: Python :: Implementation :: PyPy
Requires-Python: >=3.7
License-File: LICENSE.rst
Requires-Dist: build>=0.1
Requires-Dist: setuptools
Requires-Dist: tomli; python_version < "3.11"
Provides-Extra: test
Requires-Dist: pytest; extra == "test"
Requires-Dist: wheel; extra == "test"
Requires-Dist: mock>=3.0.0; python_version == "3.7" and extra == "test"
